{
  "parent": "minecraft:item/handheld_rod",
  "gui_light": "front",
  "textures": {
    "layer0": "minecraft:item/warped_fungus_on_a_stick"
  },
  "overrides": [
    {
      "predicate": {
        "custom_model_data": 10000
      },
      "model": "minecraft:item/potionstick"
    },
    {
      "predicate": {
        "custom_model_data": 10001
      },
      "model": "minecraft:item/potion/awkward_potion"
    },
    {
      "predicate": {
        "custom_model_data": 10002
      },
      "model": "minecraft:item/potion/empty_potion"
    },
    {
      "predicate": {
        "custom_model_data": 10003
      },
      "model": "minecraft:item/potion/fire_resistance_potion"
    },
    {
      "predicate": {
        "custom_model_data": 10004
      },
      "model": "minecraft:item/potion/harming_potion"
    },
    {
      "predicate": {
        "custom_model_data": 10005
      },
      "model": "minecraft:item/potion/healing_potion"
    },
    {
      "predicate": {
        "custom_model_data": 10006
      },
      "model": "minecraft:item/potion/invisibility_potion"
    },
    {
      "predicate": {
        "custom_model_data": 10007
      },
      "model": "minecraft:item/potion/leaping_potion"
    },
    {
      "predicate": {
        "custom_model_data": 10008
      },
      "model": "minecraft:item/potion/luck_potion"
    },
    {
      "predicate": {
        "custom_model_data": 10009
      },
      "model": "minecraft:item/potion/mundane_potion"
    },
    {
      "predicate": {
        "custom_model_data": 10010
      },
      "model": "minecraft:item/potion/night_vision_potion"
    },
    {
      "predicate": {
        "custom_model_data": 10011
      },
      "model": "minecraft:item/potion/regeneration_potion"
    },
    {
      "predicate": {
        "custom_model_data": 10012
      },
      "model": "minecraft:item/potion/slowness_potion"
    },
    {
      "predicate": {
        "custom_model_data": 10013
      },
      "model": "minecraft:item/potion/slow_falling_potion"
    },
    {
      "predicate": {
        "custom_model_data": 10014
      },
      "model": "minecraft:item/potion/strength_potion"
    },
    {
      "predicate": {
        "custom_model_data": 10015
      },
      "model": "minecraft:item/potion/swiftness_potion"
    },
    {
      "predicate": {
        "custom_model_data": 10016
      },
      "model": "minecraft:item/potion/thick_potion"
    },
    {
      "predicate": {
        "custom_model_data": 10017
      },
      "model": "minecraft:item/potion/turtle_master_potion"
    },
    {
      "predicate": {
        "custom_model_data": 10018
      },
      "model": "minecraft:item/potion/water_potion"
    },
    {
      "predicate": {
        "custom_model_data": 10019
      },
      "model": "minecraft:item/potion/water_breathing_potion"
    },
    {
      "predicate": {
        "custom_model_data": 10020
      },
      "model": "minecraft:item/potion/weakness_potion"
    },
    {
      "predicate": {
        "custom_model_data": 10021
      },
      "model": "minecraft:item/potion/harming_potion"
    },
    {
      "predicate": {
        "custom_model_data": 10022
      },
      "model": "minecraft:item/potion/healing_potion"
    },
    {
      "predicate": {
        "custom_model_data": 10023
      },
      "model": "minecraft:item/potion/leaping_potion"
    },
    {
      "predicate": {
        "custom_model_data": 10024
      },
      "model": "minecraft:item/potion/poison_potion"
    },
    {
      "predicate": {
        "custom_model_data": 10025
      },
      "model": "minecraft:item/potion/regeneration_potion"
    },
    {
      "predicate": {
        "custom_model_data": 10026
      },
      "model": "minecraft:item/potion/slowness_potion"
    },
    {
      "predicate": {
        "custom_model_data": 10027
      },
      "model": "minecraft:item/potion/strength_potion"
    },
    {
      "predicate": {
        "custom_model_data": 10028
      },
      "model": "minecraft:item/potion/swiftness_potion"
    },
    {
      "predicate": {
        "custom_model_data": 10029
      },
      "model": "minecraft:item/potion/turtle_master_potion"
    },
    {
      "predicate": {
        "custom_model_data": 10030
      },
      "model": "minecraft:item/potion/fire_resistance_potion"
    },
    {
      "predicate": {
        "custom_model_data": 10031
      },
      "model": "minecraft:item/potion/invisibility_potion"
    },
    {
      "predicate": {
        "custom_model_data": 10032
      },
      "model": "minecraft:item/potion/leaping_potion"
    },
    {
      "predicate": {
        "custom_model_data": 10033
      },
      "model": "minecraft:item/potion/night_vision_potion"
    },
    {
      "predicate": {
        "custom_model_data": 10034
      },
      "model": "minecraft:item/potion/poison_potion"
    },
    {
      "predicate": {
        "custom_model_data": 10035
      },
      "model": "minecraft:item/potion/regeneration_potion"
    },
    {
      "predicate": {
        "custom_model_data": 10036
      },
      "model": "minecraft:item/potion/slowness_potion"
    },
    {
      "predicate": {
        "custom_model_data": 10037
      },
      "model": "minecraft:item/potion/slow_falling_potion"
    },
    {
      "predicate": {
        "custom_model_data": 10038
      },
      "model": "minecraft:item/potion/strength_potion"
    },
    {
      "predicate": {
        "custom_model_data": 10039
      },
      "model": "minecraft:item/potion/swiftness_potion"
    },
    {
      "predicate": {
        "custom_model_data": 10040
      },
      "model": "minecraft:item/potion/turtle_master_potion"
    },
    {
      "predicate": {
        "custom_model_data": 10041
      },
      "model": "minecraft:item/potion/water_breathing_potion"
    },
    {
      "predicate": {
        "custom_model_data": 10042
      },
      "model": "minecraft:item/potion/weakness_potion"
    },
    {
      "predicate": {
        "custom_model_data": 10043
      },
      "model": "minecraft:item/potion/poison_potion"
    },
    {
      "predicate": {
        "custom_model_data": 10101
      },
      "model": "minecraft:item/potion/splash/awkward_potion"
    },
    {
      "predicate": {
        "custom_model_data": 10102
      },
      "model": "minecraft:item/potion/splash/empty_potion"
    },
    {
      "predicate": {
        "custom_model_data": 10103
      },
      "model": "minecraft:item/potion/splash/fire_resistance_potion"
    },
    {
      "predicate": {
        "custom_model_data": 10104
      },
      "model": "minecraft:item/potion/splash/harming_potion"
    },
    {
      "predicate": {
        "custom_model_data": 10105
      },
      "model": "minecraft:item/potion/splash/healing_potion"
    },
    {
      "predicate": {
        "custom_model_data": 10106
      },
      "model": "minecraft:item/potion/splash/invisibility_potion"
    },
    {
      "predicate": {
        "custom_model_data": 10107
      },
      "model": "minecraft:item/potion/splash/leaping_potion"
    },
    {
      "predicate": {
        "custom_model_data": 10108
      },
      "model": "minecraft:item/potion/splash/luck_potion"
    },
    {
      "predicate": {
        "custom_model_data": 10109
      },
      "model": "minecraft:item/potion/splash/mundane_potion"
    },
    {
      "predicate": {
        "custom_model_data": 10110
      },
      "model": "minecraft:item/potion/splash/night_vision_potion"
    },
    {
      "predicate": {
        "custom_model_data": 10111
      },
      "model": "minecraft:item/potion/splash/regeneration_potion"
    },
    {
      "predicate": {
        "custom_model_data": 10112
      },
      "model": "minecraft:item/potion/splash/slowness_potion"
    },
    {
      "predicate": {
        "custom_model_data": 10113
      },
      "model": "minecraft:item/potion/splash/slow_falling_potion"
    },
    {
      "predicate": {
        "custom_model_data": 10114
      },
      "model": "minecraft:item/potion/splash/strength_potion"
    },
    {
      "predicate": {
        "custom_model_data": 10115
      },
      "model": "minecraft:item/potion/splash/swiftness_potion"
    },
    {
      "predicate": {
        "custom_model_data": 10116
      },
      "model": "minecraft:item/potion/splash/thick_potion"
    },
    {
      "predicate": {
        "custom_model_data": 10117
      },
      "model": "minecraft:item/potion/splash/turtle_master_potion"
    },
    {
      "predicate": {
        "custom_model_data": 10118
      },
      "model": "minecraft:item/potion/splash/water_potion"
    },
    {
      "predicate": {
        "custom_model_data": 10119
      },
      "model": "minecraft:item/potion/splash/water_breathing_potion"
    },
    {
      "predicate": {
        "custom_model_data": 10120
      },
      "model": "minecraft:item/potion/splash/weakness_potion"
    },
    {
      "predicate": {
        "custom_model_data": 10121
      },
      "model": "minecraft:item/potion/splash/harming_potion"
    },
    {
      "predicate": {
        "custom_model_data": 10122
      },
      "model": "minecraft:item/potion/splash/healing_potion"
    },
    {
      "predicate": {
        "custom_model_data": 10123
      },
      "model": "minecraft:item/potion/splash/leaping_potion"
    },
    {
      "predicate": {
        "custom_model_data": 10124
      },
      "model": "minecraft:item/potion/splash/poison_potion"
    },
    {
      "predicate": {
        "custom_model_data": 10125
      },
      "model": "minecraft:item/potion/splash/regeneration_potion"
    },
    {
      "predicate": {
        "custom_model_data": 10126
      },
      "model": "minecraft:item/potion/splash/slowness_potion"
    },
    {
      "predicate": {
        "custom_model_data": 10127
      },
      "model": "minecraft:item/potion/splash/strength_potion"
    },
    {
      "predicate": {
        "custom_model_data": 10128
      },
      "model": "minecraft:item/potion/splash/swiftness_potion"
    },
    {
      "predicate": {
        "custom_model_data": 10129
      },
      "model": "minecraft:item/potion/splash/turtle_master_potion"
    },
    {
      "predicate": {
        "custom_model_data": 10130
      },
      "model": "minecraft:item/potion/splash/fire_resistance_potion"
    },
    {
      "predicate": {
        "custom_model_data": 10131
      },
      "model": "minecraft:item/potion/splash/invisibility_potion"
    },
    {
      "predicate": {
        "custom_model_data": 10132
      },
      "model": "minecraft:item/potion/splash/leaping_potion"
    },
    {
      "predicate": {
        "custom_model_data": 10133
      },
      "model": "minecraft:item/potion/splash/night_vision_potion"
    },
    {
      "predicate": {
        "custom_model_data": 10134
      },
      "model": "minecraft:item/potion/splash/poison_potion"
    },
    {
      "predicate": {
        "custom_model_data": 10135
      },
      "model": "minecraft:item/potion/splash/regeneration_potion"
    },
    {
      "predicate": {
        "custom_model_data": 10136
      },
      "model": "minecraft:item/potion/splash/slowness_potion"
    },
    {
      "predicate": {
        "custom_model_data": 10137
      },
      "model": "minecraft:item/potion/splash/slow_falling_potion"
    },
    {
      "predicate": {
        "custom_model_data": 10138
      },
      "model": "minecraft:item/potion/splash/strength_potion"
    },
    {
      "predicate": {
        "custom_model_data": 10139
      },
      "model": "minecraft:item/potion/splash/swiftness_potion"
    },
    {
      "predicate": {
        "custom_model_data": 10140
      },
      "model": "minecraft:item/potion/splash/turtle_master_potion"
    },
    {
      "predicate": {
        "custom_model_data": 10141
      },
      "model": "minecraft:item/potion/splash/water_breathing_potion"
    },
    {
      "predicate": {
        "custom_model_data": 10142
      },
      "model": "minecraft:item/potion/splash/weakness_potion"
    },
    {
      "predicate": {
        "custom_model_data": 10143
      },
      "model": "minecraft:item/potion/splash/poison_potion"
    },
    {
      "predicate": {
        "custom_model_data": 10201
      },
      "model": "minecraft:item/potion/lingering/awkward_potion"
    },
    {
      "predicate": {
        "custom_model_data": 10202
      },
      "model": "minecraft:item/potion/lingering/empty_potion"
    },
    {
      "predicate": {
        "custom_model_data": 10203
      },
      "model": "minecraft:item/potion/lingering/fire_resistance_potion"
    },
    {
      "predicate": {
        "custom_model_data": 10204
      },
      "model": "minecraft:item/potion/lingering/harming_potion"
    },
    {
      "predicate": {
        "custom_model_data": 10205
      },
      "model": "minecraft:item/potion/lingering/healing_potion"
    },
    {
      "predicate": {
        "custom_model_data": 10206
      },
      "model": "minecraft:item/potion/lingering/invisibility_potion"
    },
    {
      "predicate": {
        "custom_model_data": 10207
      },
      "model": "minecraft:item/potion/lingering/leaping_potion"
    },
    {
      "predicate": {
        "custom_model_data": 10208
      },
      "model": "minecraft:item/potion/lingering/luck_potion"
    },
    {
      "predicate": {
        "custom_model_data": 10209
      },
      "model": "minecraft:item/potion/lingering/mundane_potion"
    },
    {
      "predicate": {
        "custom_model_data": 10210
      },
      "model": "minecraft:item/potion/lingering/night_vision_potion"
    },
    {
      "predicate": {
        "custom_model_data": 10211
      },
      "model": "minecraft:item/potion/lingering/regeneration_potion"
    },
    {
      "predicate": {
        "custom_model_data": 10212
      },
      "model": "minecraft:item/potion/lingering/slowness_potion"
    },
    {
      "predicate": {
        "custom_model_data": 10213
      },
      "model": "minecraft:item/potion/lingering/slow_falling_potion"
    },
    {
      "predicate": {
        "custom_model_data": 10214
      },
      "model": "minecraft:item/potion/lingering/strength_potion"
    },
    {
      "predicate": {
        "custom_model_data": 10215
      },
      "model": "minecraft:item/potion/lingering/swiftness_potion"
    },
    {
      "predicate": {
        "custom_model_data": 10216
      },
      "model": "minecraft:item/potion/lingering/thick_potion"
    },
    {
      "predicate": {
        "custom_model_data": 10217
      },
      "model": "minecraft:item/potion/lingering/turtle_master_potion"
    },
    {
      "predicate": {
        "custom_model_data": 10218
      },
      "model": "minecraft:item/potion/lingering/water_breathing_potion"
    },
    {
      "predicate": {
        "custom_model_data": 10219
      },
      "model": "minecraft:item/potion/lingering/water_potion"
    },
    {
      "predicate": {
        "custom_model_data": 10220
      },
      "model": "minecraft:item/potion/lingering/weakness_potion"
    },
    {
      "predicate": {
        "custom_model_data": 10221
      },
      "model": "minecraft:item/potion/lingering/harming_potion"
    },
    {
      "predicate": {
        "custom_model_data": 10222
      },
      "model": "minecraft:item/potion/lingering/healing_potion"
    },
    {
      "predicate": {
        "custom_model_data": 10223
      },
      "model": "minecraft:item/potion/lingering/leaping_potion"
    },
    {
      "predicate": {
        "custom_model_data": 10224
      },
      "model": "minecraft:item/potion/lingering/poison_potion"
    },
    {
      "predicate": {
        "custom_model_data": 10225
      },
      "model": "minecraft:item/potion/lingering/regeneration_potion"
    },
    {
      "predicate": {
        "custom_model_data": 10226
      },
      "model": "minecraft:item/potion/lingering/slowness_potion"
    },
    {
      "predicate": {
        "custom_model_data": 10227
      },
      "model": "minecraft:item/potion/lingering/strength_potion"
    },
    {
      "predicate": {
        "custom_model_data": 10228
      },
      "model": "minecraft:item/potion/lingering/swiftness_potion"
    },
    {
      "predicate": {
        "custom_model_data": 10229
      },
      "model": "minecraft:item/potion/lingering/turtle_master_potion"
    },
    {
      "predicate": {
        "custom_model_data": 10230
      },
      "model": "minecraft:item/potion/lingering/fire_resistance_potion"
    },
    {
      "predicate": {
        "custom_model_data": 10231
      },
      "model": "minecraft:item/potion/lingering/invisibility_potion"
    },
    {
      "predicate": {
        "custom_model_data": 10232
      },
      "model": "minecraft:item/potion/lingering/leaping_potion"
    },
    {
      "predicate": {
        "custom_model_data": 10233
      },
      "model": "minecraft:item/potion/lingering/night_vision_potion"
    },
    {
      "predicate": {
        "custom_model_data": 10234
      },
      "model": "minecraft:item/potion/lingering/poison_potion"
    },
    {
      "predicate": {
        "custom_model_data": 10235
      },
      "model": "minecraft:item/potion/lingering/regeneration_potion"
    },
    {
      "predicate": {
        "custom_model_data": 10236
      },
      "model": "minecraft:item/potion/lingering/slowness_potion"
    },
    {
      "predicate": {
        "custom_model_data": 10237
      },
      "model": "minecraft:item/potion/lingering/slow_falling_potion"
    },
    {
      "predicate": {
        "custom_model_data": 10238
      },
      "model": "minecraft:item/potion/lingering/strength_potion"
    },
    {
      "predicate": {
        "custom_model_data": 10239
      },
      "model": "minecraft:item/potion/lingering/swiftness_potion"
    },
    {
      "predicate": {
        "custom_model_data": 10240
      },
      "model": "minecraft:item/potion/lingering/turtle_master_potion"
    },
    {
      "predicate": {
        "custom_model_data": 10241
      },
      "model": "minecraft:item/potion/lingering/water_breathing_potion"
    },
    {
      "predicate": {
        "custom_model_data": 10242
      },
      "model": "minecraft:item/potion/lingering/weakness_potion"
    },
    {
      "predicate": {
        "custom_model_data": 10243
      },
      "model": "minecraft:item/potion/lingering/poison_potion"
    }
  ]
}
